ace_client/__init__.py
ace_client/ace.py
ace_client/invoke.py
ace_client/py.typed
ace_client-0.1.2.dist-info/METADATA
ace_client-0.1.2.dist-info/WHEEL
ace_client-0.1.2.dist-info/licenses/LICENSE
ace_client-0.1.2.dist-info/RECORD
