Metadata-Version: 2.4
Name: ace-client
Version: 0.1.2
Summary: CLI型AIエージェントACEをPythonから簡単に利用するためのラッパーライブラリ
Project-URL: Homepage, https://github.com/kurusugawa-computer/ace-py
Project-URL: Repository, https://github.com/kurusugawa-computer/ace-py
Project-URL: Documentation, https://github.com/kurusugawa-computer/ace-py#readme
Author: Kurusugawa Computer
License: MIT
License-File: LICENSE
Keywords: ace,agent,ai,llm,mcp
Classifier: Development Status :: 4 - Beta
Classifier: Intended Audience :: Developers
Classifier: License :: OSI Approved :: MIT License
Classifier: Operating System :: OS Independent
Classifier: Programming Language :: Python :: 3
Classifier: Programming Language :: Python :: 3.12
Classifier: Programming Language :: Python :: 3.13
Classifier: Topic :: Software Development :: Libraries :: Python Modules
Classifier: Typing :: Typed
Requires-Python: >=3.12
Requires-Dist: mcp>=1.0.0
Requires-Dist: msgspec>=0.18.0
